ms_validator/__init__.py
ms_validator/param_validation.py
ms_validator-0.2.0.dist-info/METADATA
ms_validator-0.2.0.dist-info/WHEEL
ms_validator-0.2.0.dist-info/top_level.txt
ms_validator-0.2.0.dist-info/RECORD
