Metadata-Version: 2.4
Name: ms_validator
Version: 0.2.0
Summary: A package for validating .
Author: Jiwang Liu
Requires-Python: >=3.8
